AUTHORS
ChangeLog
MANIFEST.in
README.md
build-rpm.sh
requirements.txt
setup.cfg
setup.py
etc/hostha/api-paste.ini
etc/hostha/hostha.conf
etc/hostha/policy.json
etc/logrotate.d/hostha
hostha/__init__.py
hostha/add.py
hostha.egg-info/PKG-INFO
hostha.egg-info/SOURCES.txt
hostha.egg-info/dependency_links.txt
hostha.egg-info/entry_points.txt
hostha.egg-info/not-zip-safe
hostha.egg-info/pbr.json
hostha.egg-info/requires.txt
hostha.egg-info/top_level.txt
package/hostha.spec
package/systemd/hostha-api.service
package/systemd/hostha-hostha.service